iopy/__init__.py
iopy/fx2.py
iopy/prologix.py
iopy/smdp.py
iopy/version.py
iopy-0.2.4.dist-info/LICENSE.txt
iopy-0.2.4.dist-info/METADATA
iopy-0.2.4.dist-info/WHEEL
iopy-0.2.4.dist-info/top_level.txt
iopy-0.2.4.dist-info/RECORD
